m4_utils/__init__.py
m4_utils/feature_calculators.py
m4_utils/metrics.py
m4_utils/plots.py
m4_utils/s3_client.py
m4_utils/utils.py
m4_utils/transformers/__init__.py
m4_utils/transformers/column_diff.py
m4_utils/transformers/column_equality.py
m4_utils/transformers/column_time_diff.py
m4_utils/transformers/feature_union.py
m4_utils/transformers/fill_na.py
m4_utils/transformers/identity.py
m4_utils/transformers/standard_scaler.py
m4_utils/transformers/time_normalization.py
m4_utils/transformers/time_period_features.py
m4_utils/transformers/to_datetime.py
m4_utils-0.0.15.dist-info/METADATA
m4_utils-0.0.15.dist-info/WHEEL
m4_utils-0.0.15.dist-info/top_level.txt
m4_utils-0.0.15.dist-info/RECORD
