Metadata-Version: 2.1
Name: m4-utils
Version: 0.0.15
Summary: Biblioteca com funções de uso comum em projetos de aprendizado de máquina e ciencia de dados.
Author: SERVICE PREVENTION
Author-email: 
Keywords: Utility Functions,Data Science
Requires-Dist: absl-py (>=1.4.0)
Requires-Dist: adal (>=1.2.7)
Requires-Dist: aenum (>=3.1.11)
Requires-Dist: aiohttp (>=3.8.1)
Requires-Dist: aiohttp-cors (>=0.7.0)
Requires-Dist: aiorwlock (>=1.3.0)
Requires-Dist: aiosignal (>=1.3.1)
Requires-Dist: alog (>=0.9.13)
Requires-Dist: ansiwrap (>=0.8.4)
Requires-Dist: anyio (>=3.6.2)
Requires-Dist: argparse (>=1.4.0)
Requires-Dist: asgiref (>=3.6.0)
Requires-Dist: asn1crypto (>=1.5.1)
Requires-Dist: asttokens (>=2.2.1)
Requires-Dist: async-timeout (>=4.0.2)
Requires-Dist: attrs (>=22.2.0)
Requires-Dist: avro (>=1.11.1)
Requires-Dist: awswrangler (>=2.19.0)
Requires-Dist: azure-core (>=1.26.2)
Requires-Dist: azure-identity (>=1.12.0)
Requires-Dist: azure-storage-blob (>=12.9.0)
Requires-Dist: azure-storage-file-share (>=12.7.0)
Requires-Dist: backcall (>=0.2.0)
Requires-Dist: backoff (>=2.2.1)
Requires-Dist: beautifulsoup4 (>=4.11.2)
Requires-Dist: blessed (>=1.19.1)
Requires-Dist: boto3 (>=1.26.60)
Requires-Dist: botocore (>=1.29.60)
Requires-Dist: cachetools (>=5.3.0)
Requires-Dist: catboost (>=1.1.1)
Requires-Dist: certifi (>=2022.12.7)
Requires-Dist: cffi (>=1.15.1)
Requires-Dist: charset-normalizer (>=2.1.1)
Requires-Dist: click (>=8.0.4)
Requires-Dist: cloudevents (>=1.9.0)
Requires-Dist: cloudpickle (>=2.2.1)
Requires-Dist: colorful (>=0.5.5)
Requires-Dist: comm (>=0.1.2)
Requires-Dist: contourpy (>=1.0.7)
Requires-Dist: cryptography (>=39.0.0)
Requires-Dist: cycler (>=0.11.0)
Requires-Dist: debugpy (>=1.6.6)
Requires-Dist: decorator (>=5.1.1)
Requires-Dist: deprecated (>=1.2.13)
Requires-Dist: deprecation (>=2.1.0)
Requires-Dist: distlib (>=0.3.6)
Requires-Dist: docker (>=6.0.1)
Requires-Dist: docstring-parser (>=0.15)
Requires-Dist: entrypoints (>=0.4)
Requires-Dist: et-xmlfile (>=1.1.0)
Requires-Dist: executing (>=1.2.0)
Requires-Dist: fastapi (>=0.88.0)
Requires-Dist: fastjsonschema (>=2.16.2)
Requires-Dist: filelock (>=3.9.0)
Requires-Dist: fire (>=0.5.0)
Requires-Dist: fonttools (>=4.38.0)
Requires-Dist: frozenlist (>=1.3.3)
Requires-Dist: google-api-core (>=2.11.0)
Requires-Dist: google-api-python-client (>=1.12.11)
Requires-Dist: google-auth (>=2.16.0)
Requires-Dist: google-auth-httplib2 (>=0.1.0)
Requires-Dist: google-cloud-core (>=2.3.2)
Requires-Dist: google-cloud-storage (>=2.7.0)
Requires-Dist: google-crc32c (>=1.5.0)
Requires-Dist: google-resumable-media (>=2.4.1)
Requires-Dist: googleapis-common-protos (>=1.58.0)
Requires-Dist: gpustat (>=1.0.0)
Requires-Dist: graphviz (>=0.20.1)
Requires-Dist: gremlinpython (>=3.6.2)
Requires-Dist: grpcio (>=1.43.0)
Requires-Dist: h11 (>=0.14.0)
Requires-Dist: httpcore (>=0.16.3)
Requires-Dist: httplib2 (>=0.21.0)
Requires-Dist: httpx (>=0.23.3)
Requires-Dist: idna (>=3.4)
Requires-Dist: imbalanced-learn (>=0.10.1)
Requires-Dist: importlib-metadata (>=6.0.0)
Requires-Dist: ipykernel (>=6.20.2)
Requires-Dist: ipython (>=8.9.0)
Requires-Dist: ipywidgets (>=8.0.4)
Requires-Dist: isodate (>=0.6.1)
Requires-Dist: jedi (>=0.18.2)
Requires-Dist: jmespath (>=1.0.1)
Requires-Dist: joblib (>=1.2.0)
Requires-Dist: jsonpath-ng (>=1.5.3)
Requires-Dist: jsonschema (>=3.2.0)
Requires-Dist: jupyter-client (>=8.0.2)
Requires-Dist: jupyter-core (>=5.2.0)
Requires-Dist: jupyterlab-widgets (>=3.0.5)
Requires-Dist: kfmd (>=0.1.8)
Requires-Dist: kfp (>=1.8.18)
Requires-Dist: kfp-pipeline-spec (>=0.1.16)
Requires-Dist: kfp-server-api (>=1.8.5)
Requires-Dist: kiwisolver (>=1.4.4)
Requires-Dist: kserve (>=0.10.0)
Requires-Dist: kubernetes (>=19.15.0)
Requires-Dist: lxml (>=4.9.2)
Requires-Dist: matplotlib (>=3.6.3)
Requires-Dist: matplotlib-inline (>=0.1.6)
Requires-Dist: minio (>=7.1.3)
Requires-Dist: msal (>=1.20.0)
Requires-Dist: msal-extensions (>=1.0.0)
Requires-Dist: msgpack (>=1.0.4)
Requires-Dist: msrest (>=0.7.1)
Requires-Dist: multidict (>=6.0.4)
Requires-Dist: nbclient (>=0.7.2)
Requires-Dist: nbformat (>=5.7.3)
Requires-Dist: nest-asyncio (>=1.5.6)
Requires-Dist: numpy (>=1.21.6)
Requires-Dist: nvidia-ml-py (>=11.495.46)
Requires-Dist: oauthlib (>=3.2.2)
Requires-Dist: opencensus (>=0.11.1)
Requires-Dist: opencensus-context (>=0.1.3)
Requires-Dist: openpyxl (>=3.0.10)
Requires-Dist: opensearch-py (>=2.1.1)
Requires-Dist: orjson (>=3.8.5)
Requires-Dist: packaging (>=23.0)
Requires-Dist: pandas (>=1.5.1)
Requires-Dist: papermill (>=2.4.0)
Requires-Dist: parso (>=0.8.3)
Requires-Dist: pexpect (>=4.8.0)
Requires-Dist: pg8000 (>=1.29.4)
Requires-Dist: pickleshare (>=0.7.5)
Requires-Dist: pillow (>=9.4.0)
Requires-Dist: platformdirs (>=2.6.2)
Requires-Dist: plotly (>=5.13.0)
Requires-Dist: ply (>=3.11)
Requires-Dist: portalocker (>=2.7.0)
Requires-Dist: progressbar2 (>=4.2.0)
Requires-Dist: prometheus-client (>=0.13.1)
Requires-Dist: prompt-toolkit (>=3.0.36)
Requires-Dist: protobuf (>=3.19.6)
Requires-Dist: psutil (>=5.9.4)
Requires-Dist: ptyprocess (>=0.7.0)
Requires-Dist: pure-eval (>=0.2.2)
Requires-Dist: py-spy (>=0.3.14)
Requires-Dist: pyarrow (>=10.0.1)
Requires-Dist: pyasn1 (>=0.4.8)
Requires-Dist: pyasn1-modules (>=0.2.8)
Requires-Dist: pycparser (>=2.21)
Requires-Dist: pydantic (>=1.10.4)
Requires-Dist: pygments (>=2.14.0)
Requires-Dist: pyjwt[crypto] (>=2.6.0)
Requires-Dist: pymysql (>=1.0.2)
Requires-Dist: pyparsing (>=3.0.9)
Requires-Dist: pyrsistent (>=0.19.3)
Requires-Dist: python-dateutil (>=2.8.2)
Requires-Dist: python-rapidjson (>=1.9)
Requires-Dist: python-utils (>=3.4.5)
Requires-Dist: pytz (>=2022.7.1)
Requires-Dist: pyyaml (>=5.4.1)
Requires-Dist: pyzmq (>=25.0.0)
Requires-Dist: ray[serve] (>=2.0.0)
Requires-Dist: redshift-connector (>=2.0.910)
Requires-Dist: requests (>=2.28.2)
Requires-Dist: requests-aws4auth (>=1.2.1)
Requires-Dist: requests-oauthlib (>=1.3.1)
Requires-Dist: requests-toolbelt (>=0.10.1)
Requires-Dist: rfc3986[idna2008] (>=1.5.0)
Requires-Dist: rsa (>=4.9)
Requires-Dist: s3transfer (>=0.6.0)
Requires-Dist: scikit-learn (>=1.2.1)
Requires-Dist: scipy (>=1.10.0)
Requires-Dist: scramp (>=1.4.4)
Requires-Dist: seaborn (>=0.12.2)
Requires-Dist: six (>=1.16.0)
Requires-Dist: smart-open (>=6.3.0)
Requires-Dist: sniffio (>=1.3.0)
Requires-Dist: soupsieve (>=2.3.2.post1)
Requires-Dist: stack-data (>=0.6.2)
Requires-Dist: starlette (>=0.22.0)
Requires-Dist: strip-hints (>=0.1.10)
Requires-Dist: table-logger (>=0.3.6)
Requires-Dist: tabulate (>=0.9.0)
Requires-Dist: tenacity (>=8.1.0)
Requires-Dist: termcolor (>=2.2.0)
Requires-Dist: textwrap3 (>=0.9.2)
Requires-Dist: threadpoolctl (>=3.1.0)
Requires-Dist: timing-asgi (>=0.3.0)
Requires-Dist: tornado (>=6.2)
Requires-Dist: tqdm (>=4.64.1)
Requires-Dist: traitlets (>=5.9.0)
Requires-Dist: tritonclient (>=2.18.0)
Requires-Dist: typer (>=0.7.0)
Requires-Dist: typing-extensions (>=4.4.0)
Requires-Dist: uritemplate (>=3.0.1)
Requires-Dist: urllib3 (>=1.26.14)
Requires-Dist: uvicorn (>=0.16.0)
Requires-Dist: virtualenv (>=20.17.1)
Requires-Dist: wcwidth (>=0.2.6)
Requires-Dist: websocket-client (>=1.5.0)
Requires-Dist: wheel (>=0.38.4)
Requires-Dist: widgetsnbextension (>=4.0.5)
Requires-Dist: wrapt (>=1.14.1)
Requires-Dist: xgboost (>=1.7.3)
Requires-Dist: yarl (>=1.8.2)
Requires-Dist: zipp (>=3.12.0)
